cjm_fasthtml_byok/__init__.py
cjm_fasthtml_byok/_modidx.py
cjm_fasthtml_byok/components/__init__.py
cjm_fasthtml_byok/components/alerts.py
cjm_fasthtml_byok/components/forms.py
cjm_fasthtml_byok/core/__init__.py
cjm_fasthtml_byok/core/security.py
cjm_fasthtml_byok/core/storage.py
cjm_fasthtml_byok/core/types.py
cjm_fasthtml_byok/middleware/__init__.py
cjm_fasthtml_byok/middleware/beforeware.py
cjm_fasthtml_byok/utils/__init__.py
cjm_fasthtml_byok/utils/helpers.py
cjm_fasthtml_byok-0.0.3.dist-info/licenses/LICENSE
cjm_fasthtml_byok-0.0.3.dist-info/METADATA
cjm_fasthtml_byok-0.0.3.dist-info/WHEEL
cjm_fasthtml_byok-0.0.3.dist-info/entry_points.txt
cjm_fasthtml_byok-0.0.3.dist-info/top_level.txt
cjm_fasthtml_byok-0.0.3.dist-info/RECORD
