Metadata-Version: 2.4
Name: cjm-fasthtml-byok
Version: 0.0.3
Summary: Secure API key management for FastHTML applications with encrypted storage, session/database persistence, and built-in UI components.
Home-page: https://github.com/cj-mills/cjm-fasthtml-byok
Author: Christian J. Mills
Author-email: 9126128+cj-mills@users.noreply.github.com
License: Apache Software License 2.0
Keywords: nbdev jupyter notebook python
Classifier: Development Status :: 4 - Beta
Classifier: Intended Audience :: Developers
Classifier: Natural Language :: English
Classifier: Programming Language :: Python :: 3.9
Classifier: Programming Language :: Python :: 3.10
Classifier: Programming Language :: Python :: 3.11
Classifier: Programming Language :: Python :: 3.12
Classifier: License :: OSI Approved :: Apache Software License
Requires-Python: >=3.9
License-File: LICENSE
Requires-Dist: fastcore
Requires-Dist: cryptography
Requires-Dist: python-fasthtml
Requires-Dist: cjm_fasthtml_tailwind
Requires-Dist: cjm_fasthtml_daisyui
Requires-Dist: fastsql
Provides-Extra: dev
Dynamic: author
Dynamic: author-email
Dynamic: classifier
Dynamic: description
Dynamic: description-content-type
Dynamic: home-page
Dynamic: keywords
Dynamic: license
Dynamic: license-file
Dynamic: provides-extra
Dynamic: requires-dist
Dynamic: requires-python
Dynamic: summary
